Workbook

Sheet Valuation Summary
A1: MARICO BANGLADESH LIMITED | DCF VALUATION SUMMARY
A3: Valuation date | B3: 46318
A4: Latest market price input (BDT/share) | B4: =WACC!D5 -> 2668.9
A5: Model implied share price (BDT/share) | B5: =DCF!C21 -> 3032.6477
A6: Implied upside / (downside) vs market | B6: =B5/B4-1 -> 0.13629126
A8: Valuation Outputs (BDT millions unless stated)
A9: Present value of forecast UFCF | B9: =DCF!C10 -> 32836.081
A10: Present value of terminal value | B10: =DCF!C14 -> 60153.483
A11: Enterprise value | B11: =DCF!C15 -> 92989.564
A12: Add: cash and other financial assets | B12: =DCF!C16 -> 2538.84
A13: Less: interest-bearing debt | B13: =DCF!C17 -> 0
A14: Less: minority interest | B14: =DCF!C18 -> 0
A15: Equity value | B15: =DCF!C19 -> 95528.404
A16: Diluted shares outstanding (millions) | B16: =DCF!C20 -> 31.5
A18: Key Assumptions
A19: WACC | B19: =DCF!C12 -> 0.1274
A20: Perpetual growth rate | B20: =DCF!C11 -> 0.035
A21: Risk-free rate | B21: =WACC!D24 -> 0.0854
A22: Equity risk premium | B22: =WACC!D23 -> 0.07
A23: Levered beta | B23: =WACC!D17 -> 0.6
A24: Pre-tax cost of debt | B24: =WACC!D20 -> 0.115
A25: Tax rate | B25: =WACC!D21 -> 0.225
A26: Forecast period | B26: FY2026–27 to FY2030–31
A29: Important review notes
A30: • Forecast assumptions are analyst estimates, not company guidance.
A31: • Risk-free rate, ERP, beta, and cost of debt still require dated supporting sources.
A32: • Historical statement inputs have not all been independently tied to annual-report pages.
A33: • Working-capital projections imply unusually high days payable outstanding; review the operating rationale.
A34: • Cash and other financial assets are both added in the equity bridge; confirm both are excess/non-operating cash-like balances.
A35: • Sensitivity table reports implied share price (BDT/share) using WACC rows and terminal-growth columns.
A37: Primary sources
A38: Marico Bangladesh annual reports | B38: https://marico.com/bangladesh/investors/annual-report
A39: Dhaka Stock Exchange — MARICO | B39: https://www.dse.com.bd/company/MARICO

Sheet Free Cash Flow
B2: Unlevered Free Cash Flow (mm)
B3: Fiscal Year | C3: 45382 | D3: 45747 | E3: 46112 | F3: 46477 | G3: 46843 | H3: 47208 | I3: 47573 | J3: 47938
B4: Revenue | C4: ='Income Statement'!C5 -> 14524 | D4: ='Income Statement'!D5 -> 16309 | E4: ='Income Statement'!E5 -> 20712 | F4: =E4*(1+F25) -> 22783.2 | G4: =F4*(1+G25) -> 25061.52 | H4: =G4*(1+H25) -> 27317.057 | I4: =H4*(1+I25) -> 29229.251 | J4: =I4*(1+J25) -> 30690.713
B5: COGS | C5: ='Income Statement'!C7 -> 6099 | D5: ='Income Statement'!D7 -> 6598 | E5: ='Income Statement'!E7 -> 10477 | F5: =F4*F27 -> 10103.055 | G5: =G4*G27 -> 11113.36 | H5: =H4*H27 -> 12113.563 | I5: =I4*I27 -> 12961.512 | J5: =J4*J27 -> 13609.588
B6: Gross Profit | C6: =C4-C5 -> 8425 | D6: =D4-D5 -> 9711 | E6: =E4-E5 -> 10235 | F6: =F4-F5 -> 12680.145 | G6: =G4-G5 -> 13948.16 | H6: =H4-H5 -> 15203.494 | I6: =I4-I5 -> 16267.739 | J6: =J4-J5 -> 17081.126
B7: Operating Expenses
B8: Selling, General, Administrative | C8: =SUM('Income Statement'!C8,'Income Statement'!C10) -> 2314 | D8: =SUM('Income Statement'!D8,'Income Statement'!D10) -> 2667 | E8: =SUM('Income Statement'!E8,'Income Statement'!E10) -> 2617 | F8: =F4*F28 -> 3411.4327 | G8: =G4*G28 -> 3752.576 | H8: =H4*H28 -> 4090.3078 | I8: =I4*I28 -> 4376.6293 | J8: =J4*J28 -> 4595.4608
B9: Total Operating Expenses | C9: =SUM(C8) -> 2314 | D9: =SUM(D8) -> 2667 | E9: =SUM(E8) -> 2617 | F9: =F8 -> 3411.4327 | G9: =G8 -> 3752.576 | H9: =H8 -> 4090.3078 | I9: =I8 -> 4376.6293 | J9: =J8 -> 4595.4608
B10: EBITDA | C10: =C6-C9 -> 6111 | D10: =D6-D9 -> 7044 | E10: =E6-E9 -> 7618 | F10: =F6-F9 -> 9268.7125 | G10: =G6-G9 -> 10195.584 | H10: =H6-H9 -> 11113.186 | I10: =I6-I9 -> 11891.109 | J10: =J6-J9 -> 12485.665
B11: Depreciation & Amortization | C11: ='Income Statement'!C9 -> 272 | D11: ='Income Statement'!D9 -> 275 | E11: ='Income Statement'!E9 -> 262 | F11: ='Fixed Assets'!F5 -> 268.61098 | G11: ='Fixed Assets'!G5 -> 265.21236 | H11: ='Fixed Assets'!H5 -> 261.85674 | I11: ='Fixed Assets'!I5 -> 258.54357 | J11: ='Fixed Assets'!J5 -> 255.27233
B12: Operating Profit (EBIT) | C12: =C10-C11 -> 5839 | D12: =D10-D11 -> 6769 | E12: =E10-E11 -> 7356 | F12: =F10-F11 -> 9000.1015 | G12: =G10-G11 -> 9930.3714 | H12: =H10-H11 -> 10851.33 | I12: =I10-I11 -> 11632.566 | J12: =J10-J11 -> 12230.392
B13: Operating Taxes | C13: ='Income Statement'!C16 -> 1250 | D13: ='Income Statement'!D16 -> 1666 | E13: ='Income Statement'!E16 -> 1109 | F13: =F12*F29 -> 2025.0228 | G13: =G12*G29 -> 2234.3336 | H13: =H12*H29 -> 2441.5491 | I13: =I12*I29 -> 2617.3273 | J13: =J12*J29 -> 2751.8383
B14: NOPAT (Net Operating Profit After Taxes) | C14: =C12-C13 -> 4589 | D14: =D12-D13 -> 5103 | E14: =E12-E13 -> 6247 | F14: =F12-F13 -> 6975.0787 | G14: =G12-G13 -> 7696.0378 | H14: =H12-H13 -> 8409.7804 | I14: =I12-I13 -> 9015.2384 | J14: =J12-J13 -> 9478.5541
B15: (+) Depreciation & Amortization | C15: =C11 -> 272 | D15: =D11 -> 275 | E15: =E11 -> 262 | F15: ='Fixed Assets'!F5 -> 268.61098 | G15: ='Fixed Assets'!G5 -> 265.21236 | H15: ='Fixed Assets'!H5 -> 261.85674 | I15: ='Fixed Assets'!I5 -> 258.54357 | J15: ='Fixed Assets'!J5 -> 255.27233
B16: (-) Capital Expenditures | C16: ='Fixed Assets'!C6 -> 461.06 | D16: ='Fixed Assets'!D6 -> 165.62 | E16: ='Fixed Assets'!E6 -> 262.26 | F16: ='Fixed Assets'!F6 -> 247.716 | G16: ='Fixed Assets'!G6 -> 244.58175 | H16: ='Fixed Assets'!H6 -> 241.48716 | I16: ='Fixed Assets'!I6 -> 238.43173 | J16: ='Fixed Assets'!J6 -> 235.41495
B17: (-) Change in NWC | C17: =C18-('Net Working Capital'!C7-'Net Working Capital'!C13) -> 456.45 | D17: =D18-C18 -> 1772.02 | E17: =E18-D18 -> 980.43 | F17: =F18-E18 -> -3194.6128 | G17: =G18-F18 -> -440.51128 | H17: =H18-G18 -> -436.10617 | I17: =I18-H18 -> -369.72112 | J17: =J18-I18 -> -282.57257
B18: NWC | C18: =C19-C20 -> -3962.95 | D18: =D19-D20 -> -2190.93 | E18: =E19-E20 -> -1210.5 | F18: =F19-F20 -> -4405.1128 | G18: =G19-G20 -> -4845.6241 | H18: =H19-H20 -> -5281.7303 | I18: =I19-I20 -> -5651.4514 | J18: =J19-J20 -> -5934.0239
B19: Current Assets | C19: ='Net Working Capital'!D7 -> 4108.18 | D19: ='Net Working Capital'!E7 -> 3912.91 | E19: ='Net Working Capital'!F7 -> 4091.67 | F19: ='Net Working Capital'!G7 -> 5507.8172 | G19: ='Net Working Capital'!H7 -> 6058.5989 | H19: ='Net Working Capital'!I7 -> 6603.8728 | I19: ='Net Working Capital'!J7 -> 7066.1439 | J19: ='Net Working Capital'!K7 -> 7419.4511
B20: Current Liabilitites | C20: ='Net Working Capital'!D13 -> 8071.13 | D20: ='Net Working Capital'!E13 -> 6103.84 | E20: ='Net Working Capital'!F13 -> 5302.17 | F20: ='Net Working Capital'!G13 -> 9912.93 | G20: ='Net Working Capital'!H13 -> 10904.223 | H20: ='Net Working Capital'!I13 -> 11885.603 | I20: ='Net Working Capital'!J13 -> 12717.595 | J20: ='Net Working Capital'!K13 -> 13353.475
B21: Unlevered Free Cash Flow | C21: =C14+C15-C16-C17 -> 3943.49 | D21: =D14+D15-D16-D17 -> 3440.36 | E21: =E14+E15-E16-E17 -> 5266.31 | F21: =F14+F15-F16-F17 -> 10190.586 | G21: =G14+G15-G16-G17 -> 8157.1797 | H21: =H14+H15-H16-H17 -> 8866.2561 | I21: =I14+I15-I16-I17 -> 9405.0714 | J21: =J14+J15-J16-J17 -> 9780.9841
B23: Assumptions
B24: =B3 -> Fiscal Year | C24: =C3 -> 45382 | D24: =D3 -> 45747 | E24: =E3 -> 46112 | F24: =F3 -> 46477 | G24: =G3 -> 46843 | H24: =H3 -> 47208 | I24: =I3 -> 47573 | J24: =J3 -> 47938
B25: Revenue Growth | D25: =D4/C4-1 -> 0.12290003 | E25: =E4/D4-1 -> 0.26997363 | F25: 0.1 | G25: 0.1 | H25: 0.09 | I25: 0.07 | J25: 0.05
B27: COGS % of Revenue | C27: =C5/C4 -> 0.41992564 | D27: =D5/D4 -> 0.4045619 | E27: =E5/E4 -> 0.50584202 | F27: =AVERAGE(C27:E27) -> 0.44344319 | G27: =F27 -> 0.44344319 | H27: =G27 -> 0.44344319 | I27: =H27 -> 0.44344319 | J27: =I27 -> 0.44344319
B28: SG&A % of Revenue | C28: =C8/C4 -> 0.1593225 | D28: =D8/D4 -> 0.16352934 | E28: =E8/E4 -> 0.12635187 | F28: =AVERAGE(C28:E28) -> 0.14973457 | G28: =F28 -> 0.14973457 | H28: =G28 -> 0.14973457 | I28: =H28 -> 0.14973457 | J28: =I28 -> 0.14973457
B29: Tax % of EBIT | C29: =C13/C12 -> 0.21407775 | D29: =D13/D12 -> 0.24612203 | E29: =E13/E12 -> 0.15076128 | F29: 0.225 | G29: 0.225 | H29: 0.225 | I29: 0.225 | J29: 0.225

Sheet Fixed Assets
B2: Fixed Assets Schedule
B3: Fiscal Year | C3: 45382 | D3: 45747 | E3: 46112 | F3: 46477 | G3: 46843 | H3: 47208 | I3: 47573 | J3: 47938
B4: Beginning PP&E | C4: =SUM('Balance Sheet'!C11:C12) -> 1571.5 | D4: =SUM('Balance Sheet'!D11:D12) -> 1760.56 | E4: =SUM('Balance Sheet'!E11:E12) -> 1651.18 | F4: =E7 -> 1651.44 | G4: =F7 -> 1630.545 | H4: =G7 -> 1609.9144 | I4: =H7 -> 1589.5448 | J4: =I7 -> 1569.433
B5: D&A | C5: ='Income Statement'!C9 -> 272 | D5: ='Income Statement'!D9 -> 275 | E5: ='Income Statement'!E9 -> 262 | F5: =F11*F4 -> 268.61098 | G5: =G11*G4 -> 265.21236 | H5: =H11*H4 -> 261.85674 | I5: =I11*I4 -> 258.54357 | J5: =J11*J4 -> 255.27233
B6: CapEx | C6: =C7-C4+C5 -> 461.06 | D6: =D7-D4+D5 -> 165.62 | E6: =E7-E4+E5 -> 262.26 | F6: =F12*F4 -> 247.716 | G6: =G12*G4 -> 244.58175 | H6: =H12*H4 -> 241.48716 | I6: =I12*I4 -> 238.43173 | J6: =J12*J4 -> 235.41495
B7: Ending PP&E | C7: =SUM('Balance Sheet'!D11:D12) -> 1760.56 | D7: =SUM('Balance Sheet'!E11:E12) -> 1651.18 | E7: =SUM('Balance Sheet'!F11:F12) -> 1651.44 | F7: =F4-F5+F6 -> 1630.545 | G7: =G4-G5+G6 -> 1609.9144 | H7: =H4-H5+H6 -> 1589.5448 | I7: =I4-I5+I6 -> 1569.433 | J7: =J4-J5+J6 -> 1549.5756
B9: Assumptions
B10: Fiscal Year | C10: 45382 | D10: 45747 | E10: 46112 | F10: 46477 | G10: 46843 | H10: 47208 | I10: 47573 | J10: 47938
B11: D&A as a % of Beginning PP&E | C11: =C5/C4 -> 0.17308304 | D11: =D5/D4 -> 0.1562003 | E11: =E5/E4 -> 0.1586744 | F11: =AVERAGE(C11:E11) -> 0.16265258 | G11: =F11 -> 0.16265258 | H11: =G11 -> 0.16265258 | I11: =H11 -> 0.16265258 | J11: =I11 -> 0.16265258
B12: CapEx as a % of Beginning PP&E | C12: =C6/C4 -> 0.29338848 | D12: =D6/D4 -> 0.094072341 | E12: =E6/E4 -> 0.15883187 | F12: 0.15 | G12: =F12 -> 0.15 | H12: =G12 -> 0.15 | I12: =H12 -> 0.15 | J12: =I12 -> 0.15

Sheet Net Working Capital
B2: Net Working Capital
B3: Fiscal Year | C3: 45016 | D3: 45382 | E3: 45747 | F3: 46112 | G3: 46477 | H3: 46843 | I3: 47208 | J3: 47573 | K3: =K16 -> 47938
B4: Accounts Receivables | C4: ='Balance Sheet'!C6 -> 1028.62 | D4: ='Balance Sheet'!D6 -> 756.71 | E4: ='Balance Sheet'!E6 -> 962.31 | F4: ='Balance Sheet'!F6 -> 560.37 | G4: =G20*G17/360 -> 1201.4046 | H4: =H20*H17/360 -> 1321.5451 | I4: =I20*I17/360 -> 1440.4841 | J4: =J20*J17/360 -> 1541.318 | K4: =K20*K17/360 -> 1618.3839
B5: Inventory | C5: ='Balance Sheet'!C7 -> 2528.55 | D5: ='Balance Sheet'!D7 -> 3351.47 | E5: ='Balance Sheet'!E7 -> 2950.6 | F5: ='Balance Sheet'!F7 -> 3531.3 | G5: =G18*G21/360 -> 4306.4126 | H5: =H18*H21/360 -> 4737.0539 | I5: =I18*I21/360 -> 5163.3887 | J5: =J18*J21/360 -> 5524.8259 | K5: =K18*K21/360 -> 5801.0672
B6: Other Current Assets | C6: 0 | D6: 0 | E6: 0 | F6: 0 | G6: 0 | H6: 0 | I6: 0 | J6: 0 | K6: 0
B7: Current Assets | C7: =SUM(C4:C6) -> 3557.17 | D7: =SUM(D4:D6) -> 4108.18 | E7: =SUM(E4:E6) -> 3912.91 | F7: =SUM(F4:F6) -> 4091.67 | G7: =SUM(G4:G6) -> 5507.8172 | H7: =SUM(H4:H6) -> 6058.5989 | I7: =SUM(I4:I6) -> 6603.8728 | J7: =SUM(J4:J6) -> 7066.1439 | K7: =SUM(K4:K6) -> 7419.4511
B9: Accounts Payable | C9: ='Balance Sheet'!C16 -> 7106.38 | D9: ='Balance Sheet'!D16 -> 7168.2 | E9: ='Balance Sheet'!E16 -> 4897.45 | F9: ='Balance Sheet'!F16 -> 4415.03 | G9: =G18*G22/360 -> 8542.9153 | H9: =H18*H22/360 -> 9397.2069 | I9: =I18*I22/360 -> 10242.955 | J9: =J18*J22/360 -> 10959.962 | K9: =K18*K22/360 -> 11507.96
B10: Accrued Salaries and Benefits | C10: ='Balance Sheet'!C17 -> 25.89 | D10: ='Balance Sheet'!D17 -> 21.62 | E10: ='Balance Sheet'!E17 -> 48.56 | F10: ='Balance Sheet'!F17 -> 91.28 | G10: =G17*G$24 -> 60.971844 | H10: =H17*H$24 -> 67.069029 | I10: =I17*I$24 -> 73.105241 | J10: =J17*J$24 -> 78.222608 | K10: =K17*K$24 -> 82.133739
B11: ='Balance Sheet'!B18 -> Current tax and other payables | C11: ='Balance Sheet'!C18 -> 786.99 | D11: ='Balance Sheet'!D18 -> 842.44 | E11: ='Balance Sheet'!E18 -> 1099.32 | F11: ='Balance Sheet'!F18 -> 736.1 | G11: =G$17*G25 -> 1233.8389 | H11: =H$17*H25 -> 1357.2228 | I11: =I$17*I25 -> 1479.3729 | J11: =J$17*J25 -> 1582.929 | K11: =K$17*K25 -> 1662.0755
B12: ='Balance Sheet'!B21 -> Lease liabilities (current) | C12: ='Balance Sheet'!C21 -> 57.31 | D12: ='Balance Sheet'!D21 -> 38.87 | E12: ='Balance Sheet'!E21 -> 58.51 | F12: ='Balance Sheet'!F21 -> 59.76 | G12: =G$17*G26 -> 75.203903 | H12: =H$17*H26 -> 82.724293 | I12: =I$17*I26 -> 90.16948 | J12: =J$17*J26 -> 96.481343 | K12: =K$17*K26 -> 101.30541
B13: Current Liabilities | C13: =SUM(C9:C12) -> 7976.57 | D13: =SUM(D9:D12) -> 8071.13 | E13: =SUM(E9:E12) -> 6103.84 | F13: =SUM(F9:F12) -> 5302.17 | G13: =SUM(G9:G12) -> 9912.93 | H13: =SUM(H9:H12) -> 10904.223 | I13: =SUM(I9:I12) -> 11885.603 | J13: =SUM(J9:J12) -> 12717.595 | K13: =SUM(K9:K12) -> 13353.475
B15: Assumptions
B16: Fiscal Year | C16: 45016 | D16: 45382 | E16: 45747 | F16: 46112 | G16: 46477 | H16: 46843 | I16: 47208 | J16: 47573 | K16: 47938
B17: Revenue | C17: 14135.74 | D17: ='Income Statement'!C5 -> 14524 | E17: ='Income Statement'!D5 -> 16309 | F17: ='Income Statement'!E5 -> 20712 | G17: ='Free Cash Flow'!F4 -> 22783.2 | H17: ='Free Cash Flow'!G4 -> 25061.52 | I17: ='Free Cash Flow'!H4 -> 27317.057 | J17: ='Free Cash Flow'!I4 -> 29229.251 | K17: ='Free Cash Flow'!J4 -> 30690.713
B18: COGS | C18: 6811.2 | D18: ='Income Statement'!C7 -> 6099 | E18: ='Income Statement'!D7 -> 6598 | F18: ='Income Statement'!E7 -> 10477 | G18: ='Free Cash Flow'!F5 -> 10103.055 | H18: ='Free Cash Flow'!G5 -> 11113.36 | I18: ='Free Cash Flow'!H5 -> 12113.563 | J18: ='Free Cash Flow'!I5 -> 12961.512 | K18: ='Free Cash Flow'!J5 -> 13609.588
B20: Days Sales Outstanding (DSO) | C20: =C4/C17*360 -> 26.196237 | D20: =D4/D17*360 -> 18.756238 | E20: =E4/E17*360 -> 21.241744 | F20: =F4/F17*360 -> 9.7399189 | G20: =AVERAGE(C20:F20) -> 18.983534 | H20: =G20 -> 18.983534 | I20: =H20 -> 18.983534 | J20: =I20 -> 18.983534 | K20: =J20 -> 18.983534
B21: Days Inventory Outstanding (DIO) | C21: =C5/C18*360 -> 133.64429 | D21: =D5/D18*360 -> 197.8241 | E21: =E5/E18*360 -> 160.9906 | F21: =F5/F18*360 -> 121.33893 | G21: =AVERAGE(C21:F21) -> 153.44948 | H21: =G21 -> 153.44948 | I21: =H21 -> 153.44948 | J21: =I21 -> 153.44948 | K21: =J21 -> 153.44948
B22: Days Payable Outstanding (DPO) | C22: =C9/C18*360 -> 375.60148 | D22: =D9/D18*360 -> 423.11067 | E22: =E9/E18*360 -> 267.21461 | F22: =F9/F18*360 -> 151.70476 | G22: =AVERAGE(C22:F22) -> 304.40788 | H22: =G22 -> 304.40788 | I22: =H22 -> 304.40788 | J22: =I22 -> 304.40788 | K22: =J22 -> 304.40788
B24: Accrued Salaries as a % of Revenue | C24: =C10/C$17 -> 0.0018315277 | D24: =D10/D$17 -> 0.0014885706 | E24: =E10/E$17 -> 0.0029774971 | F24: =F10/F$17 -> 0.004407107 | G24: =AVERAGE(C24:F24) -> 0.0026761756 | H24: =G24 -> 0.0026761756 | I24: =H24 -> 0.0026761756 | J24: =I24 -> 0.0026761756 | K24: =J24 -> 0.0026761756
B25: Current Tax & Other Pay as a % of Revenue | C25: =C11/C$17 -> 0.055673774 | D25: =D11/D$17 -> 0.058003305 | E25: =E11/E$17 -> 0.067405727 | F25: =F11/F$17 -> 0.035539784 | G25: =AVERAGE(C25:F25) -> 0.054155647 | H25: =G25 -> 0.054155647 | I25: =H25 -> 0.054155647 | J25: =I25 -> 0.054155647 | K25: =J25 -> 0.054155647
B26: Other Current Liabilities as a % of Revenue | C26: =C12/C$17 -> 0.0040542625 | D26: =D12/D$17 -> 0.00267626 | E26: =E12/E$17 -> 0.0035875897 | F26: =F12/F$17 -> 0.0028852839 | G26: =AVERAGE(C26:F26) -> 0.003300849 | H26: =G26 -> 0.003300849 | I26: =H26 -> 0.003300849 | J26: =I26 -> 0.003300849 | K26: =J26 -> 0.003300849

Sheet DCF
B2: Unlevered Free Cash Flow (mm)
B3: Fiscal Year | D3: 45382 | E3: 45747 | F3: 46112 | G3: 46477 | H3: 46843 | I3: 47208 | J3: 47573 | K3: 47938
B4: Unlevered Free Cash Flow | D4: ='Free Cash Flow'!C21 -> 3943.49 | E4: ='Free Cash Flow'!D21 -> 3440.36 | F4: ='Free Cash Flow'!E21 -> 5266.31 | G4: ='Free Cash Flow'!F21 -> 10190.586 | H4: ='Free Cash Flow'!G21 -> 8157.1797 | I4: ='Free Cash Flow'!H21 -> 8866.2561 | J4: ='Free Cash Flow'!I21 -> 9405.0714 | K4: ='Free Cash Flow'!J21 -> 9780.9841
B6: Projection Year | G6: 1 | H6: 2 | I6: 3 | J6: 4 | K6: 5
B7: Present Value of Free Cash Flow | G7: =G4/(1+$C$12)^G6 -> 9039.0158 | H7: =H4/(1+$C$12)^H6 -> 6417.7673 | I7: =I4/(1+$C$12)^I6 -> 6187.3713 | J7: =J4/(1+$C$12)^J6 -> 5821.7021 | K7: =K4/(1+$C$12)^K6 -> 5370.224
B9: Implied Share Price Calculation | E9: Sensitivity Table
B10: Sum of PV of FCF | C10: =SUM(G7:K7) -> 32836.081
B11: Growth Rate | C11: 0.035 | G11: Growth Rate
B12: WACC | C12: =WACC!D27 -> 0.1274 | F12: =C21 -> 3032.6477 | G12: 0.02 | H12: 0.025 | I12: 0.03 | J12: 0.035 | K12: 0.04
B13: Terminal Value | C13: =K4*(1+C11)/(C12-C11) -> 109559.72 | E13: WACC | F13: =$C$12-0.01 -> 0.1174 | G13: =IF($F13<=G$12,NA(),(SUMPRODUCT($G$4:$K$4,1/(1+$F13)^$G$6:$K$6)+($K$4*(1+G$12)/($F13-G$12))/(1+$F13)^$K$6+$C$16-$C$17-$C$18)/$C$20) -> 3015.7169 | H13: =IF($F13<=H$12,NA(),(SUMPRODUCT($G$4:$K$4,1/(1+$F13)^$G$6:$K$6)+($K$4*(1+H$12)/($F13-H$12))/(1+$F13)^$K$6+$C$16-$C$17-$C$18)/$C$20) -> 3126.3733 | I13: =IF($F13<=I$12,NA(),(SUMPRODUCT($G$4:$K$4,1/(1+$F13)^$G$6:$K$6)+($K$4*(1+I$12)/($F13-I$12))/(1+$F13)^$K$6+$C$16-$C$17-$C$18)/$C$20) -> 3249.6906 | J13: =IF($F13<=J$12,NA(),(SUMPRODUCT($G$4:$K$4,1/(1+$F13)^$G$6:$K$6)+($K$4*(1+J$12)/($F13-J$12))/(1+$F13)^$K$6+$C$16-$C$17-$C$18)/$C$20) -> 3387.9736 | K13: =IF($F13<=K$12,NA(),(SUMPRODUCT($G$4:$K$4,1/(1+$F13)^$G$6:$K$6)+($K$4*(1+K$12)/($F13-K$12))/(1+$F13)^$K$6+$C$16-$C$17-$C$18)/$C$20) -> 3544.1225
B14: PV of Terminal Value | C14: =C13/(1+C12)^K6 -> 60153.483 | F14: =$C$12-0.005 -> 0.1224 | G14: =IF($F14<=G$12,NA(),(SUMPRODUCT($G$4:$K$4,1/(1+$F14)^$G$6:$K$6)+($K$4*(1+G$12)/($F14-G$12))/(1+$F14)^$K$6+$C$16-$C$17-$C$18)/$C$20) -> 2872.2309 | H14: =IF($F14<=H$12,NA(),(SUMPRODUCT($G$4:$K$4,1/(1+$F14)^$G$6:$K$6)+($K$4*(1+H$12)/($F14-H$12))/(1+$F14)^$K$6+$C$16-$C$17-$C$18)/$C$20) -> 2970.3136 | I14: =IF($F14<=I$12,NA(),(SUMPRODUCT($G$4:$K$4,1/(1+$F14)^$G$6:$K$6)+($K$4*(1+I$12)/($F14-I$12))/(1+$F14)^$K$6+$C$16-$C$17-$C$18)/$C$20) -> 3079.0113 | J14: =IF($F14<=J$12,NA(),(SUMPRODUCT($G$4:$K$4,1/(1+$F14)^$G$6:$K$6)+($K$4*(1+J$12)/($F14-J$12))/(1+$F14)^$K$6+$C$16-$C$17-$C$18)/$C$20) -> 3200.1458 | K14: =IF($F14<=K$12,NA(),(SUMPRODUCT($G$4:$K$4,1/(1+$F14)^$G$6:$K$6)+($K$4*(1+K$12)/($F14-K$12))/(1+$F14)^$K$6+$C$16-$C$17-$C$18)/$C$20) -> 3335.9812
B15: Enterprise Value | C15: =C14+C10 -> 92989.564 | F15: =$C$12 -> 0.1274 | G15: =IF($F15<=G$12,NA(),(SUMPRODUCT($G$4:$K$4,1/(1+$F15)^$G$6:$K$6)+($K$4*(1+G$12)/($F15-G$12))/(1+$F15)^$K$6+$C$16-$C$17-$C$18)/$C$20) -> 2742.1285 | H15: =IF($F15<=H$12,NA(),(SUMPRODUCT($G$4:$K$4,1/(1+$F15)^$G$6:$K$6)+($K$4*(1+H$12)/($F15-H$12))/(1+$F15)^$K$6+$C$16-$C$17-$C$18)/$C$20) -> 2829.5112 | I15: =IF($F15<=I$12,NA(),(SUMPRODUCT($G$4:$K$4,1/(1+$F15)^$G$6:$K$6)+($K$4*(1+I$12)/($F15-I$12))/(1+$F15)^$K$6+$C$16-$C$17-$C$18)/$C$20) -> 2925.8655 | J15: =IF($F15<=J$12,NA(),(SUMPRODUCT($G$4:$K$4,1/(1+$F15)^$G$6:$K$6)+($K$4*(1+J$12)/($F15-J$12))/(1+$F15)^$K$6+$C$16-$C$17-$C$18)/$C$20) -> 3032.6477 | K15: =IF($F15<=K$12,NA(),(SUMPRODUCT($G$4:$K$4,1/(1+$F15)^$G$6:$K$6)+($K$4*(1+K$12)/($F15-K$12))/(1+$F15)^$K$6+$C$16-$C$17-$C$18)/$C$20) -> 3151.6476
B16: (+) Cash and other financial assets | C16: ='Balance Sheet'!F4+'Balance Sheet'!F5 -> 2538.84 | F16: =$C$12+0.005 -> 0.1324 | G16: =IF($F16<=G$12,NA(),(SUMPRODUCT($G$4:$K$4,1/(1+$F16)^$G$6:$K$6)+($K$4*(1+G$12)/($F16-G$12))/(1+$F16)^$K$6+$C$16-$C$17-$C$18)/$C$20) -> 2623.6231 | H16: =IF($F16<=H$12,NA(),(SUMPRODUCT($G$4:$K$4,1/(1+$F16)^$G$6:$K$6)+($K$4*(1+H$12)/($F16-H$12))/(1+$F16)^$K$6+$C$16-$C$17-$C$18)/$C$20) -> 2701.8348 | I16: =IF($F16<=I$12,NA(),(SUMPRODUCT($G$4:$K$4,1/(1+$F16)^$G$6:$K$6)+($K$4*(1+I$12)/($F16-I$12))/(1+$F16)^$K$6+$C$16-$C$17-$C$18)/$C$20) -> 2787.6844 | J16: =IF($F16<=J$12,NA(),(SUMPRODUCT($G$4:$K$4,1/(1+$F16)^$G$6:$K$6)+($K$4*(1+J$12)/($F16-J$12))/(1+$F16)^$K$6+$C$16-$C$17-$C$18)/$C$20) -> 2882.3482 | K16: =IF($F16<=K$12,NA(),(SUMPRODUCT($G$4:$K$4,1/(1+$F16)^$G$6:$K$6)+($K$4*(1+K$12)/($F16-K$12))/(1+$F16)^$K$6+$C$16-$C$17-$C$18)/$C$20) -> 2987.2569
B17: (-) Debt | C17: =WACC!D9 -> 0 | F17: =$C$12+0.01 -> 0.1374 | G17: =IF($F17<=G$12,NA(),(SUMPRODUCT($G$4:$K$4,1/(1+$F17)^$G$6:$K$6)+($K$4*(1+G$12)/($F17-G$12))/(1+$F17)^$K$6+$C$16-$C$17-$C$18)/$C$20) -> 2515.2323 | H17: =IF($F17<=H$12,NA(),(SUMPRODUCT($G$4:$K$4,1/(1+$F17)^$G$6:$K$6)+($K$4*(1+H$12)/($F17-H$12))/(1+$F17)^$K$6+$C$16-$C$17-$C$18)/$C$20) -> 2585.5322 | I17: =IF($F17<=I$12,NA(),(SUMPRODUCT($G$4:$K$4,1/(1+$F17)^$G$6:$K$6)+($K$4*(1+I$12)/($F17-I$12))/(1+$F17)^$K$6+$C$16-$C$17-$C$18)/$C$20) -> 2662.3777 | J17: =IF($F17<=J$12,NA(),(SUMPRODUCT($G$4:$K$4,1/(1+$F17)^$G$6:$K$6)+($K$4*(1+J$12)/($F17-J$12))/(1+$F17)^$K$6+$C$16-$C$17-$C$18)/$C$20) -> 2746.7276 | K17: =IF($F17<=K$12,NA(),(SUMPRODUCT($G$4:$K$4,1/(1+$F17)^$G$6:$K$6)+($K$4*(1+K$12)/($F17-K$12))/(1+$F17)^$K$6+$C$16-$C$17-$C$18)/$C$20) -> 2839.7377
B18: (-) Minority Interest | C18: ='Balance Sheet'!F35 -> 0
B19: Equity Value | C19: =C15+C16-C17-C18 -> 95528.404
B20: Diluted Shares Outstanding (mm) | C20: 31.5
B21: Implied Share Price | C21: =C19/C20 -> 3032.6477

Sheet WACC
B2: Weight Average Cost OF Capital
B4: Capital Structure & Weights
B5: Share Price | D5: 2668.9
B6: Outstanding Shares | D6: 31.5
B8: Market Value OF Equity | D8: =D5*D6 -> 84070.35
B9: Total Interest-Bearing Debt | D9: 0
B11: Total Capitalization | D11: =D8+D9 -> 84070.35
C12: Weight
C13: Debt | D13: Equity
C14: =D9/D11 -> 0 | D14: =D8/D11 -> 1
B15: Taarget Debt /equity ratio | D15: 0
B16: unlevered Beta | D16: 0.6
B17: Levered Beta | D17: =D16*(1+(1-D21)*D15) -> 0.6
B19: Cost OF Debt
B20: Pre-tax Cost of Debt | D20: 0.115
B21: Tax Rate | D21: 0.225
B22: After-tax Cost of Debt | D22: =D20*(1-D21) -> 0.089125
B23: Equity Market Risk Premium (ERP) | D23: 0.07
B24: Risk Free Rate | D24: 0.0854
B25: Expected Cost of Equity | D25: =D24+(D17*D23) -> 0.1274
B27: WACC | D27: =C14*D22+D14*D25 -> 0.1274

Sheet Data Source -->
A1: Input / Data Item | B1: Period / Coverage | C1: Source / Method | D1: URL | E1: Date Accessed | F1: Model Location | G1: Notes / Audit Status
A2: Annual report / audited financial statements | B2: FY2023–24 | C2: Official Marico Bangladesh investor-relations annual report archive | D2: https://marico.com/bangladesh/investors/annual-report | E2: 46318 | F2: Income Statement; Balance Sheet; Cash Flow Statement | G2: Use the FY2023–24 report for historical inputs. Verify every figure and unit against the report before external publication.
A3: Annual report / audited financial statements | B3: FY2024–25 | C3: Official Marico Bangladesh investor-relations annual report archive | D3: https://marico.com/bangladesh/investors/annual-report | E3: 46318 | F3: Income Statement; Balance Sheet; Cash Flow Statement | G3: FY2024–25 report is listed on the official archive. Workbook figures have not been independently cross-footed to every report page.
A4: Annual report / audited financial statements | B4: FY2025–26 | C4: Official Marico Bangladesh investor-relations annual report archive | D4: https://marico.com/bangladesh/investors/annual-report | E4: 46318 | F4: Income Statement; Balance Sheet; Cash Flow Statement | G4: FY2025–26 report is listed on the official archive. Check statements and comparative figures against the PDF.
A5: Market price per share | B5: Captured 2026-10-23 | C5: Dhaka Stock Exchange company page (MARICO) | D5: https://www.dse.com.bd/company/MARICO | E5: 46318 | F5: WACC!D5 | G5: Workbook input updated to BDT 2,668.90 based on the DSE page retrieved during this review. Confirm the displayed quote/date before publishing.
A6: Shares outstanding | B6: 31.5 million | C6: Dhaka Stock Exchange company page (MARICO) | D6: https://www.dse.com.bd/company/MARICO | E6: 46318 | F6: WACC!D6; DCF!C20 | G6: DSE page reports 31,500,000 outstanding securities. Workbook uses millions of shares.
A7: Market-price cross-check (secondary) | B7: Historical / delayed market data | C7: StockAnalysis MARICO historical price page | D7: https://stockanalysis.com/quote/dse/MARICO/history/ | E7: 46318 | F7: Cross-check only | G7: Secondary source only; use DSE/company disclosures as primary sources.
A8: Risk-free rate | B8: Model assumption: 8.54% | C8: Existing workbook input; source not supplied | E8: 46318 | F8: WACC!D24 | G8: Source required. Replace with a dated Bangladesh government bond yield or another clearly justified local-currency proxy.
A9: Equity risk premium | B9: Model assumption: 7.00% | C9: Existing workbook input; source not supplied | E9: 46318 | F9: WACC!D23 | G9: Source and rationale required; do not present as independently verified.
A10: Unlevered beta | B10: Model assumption: 0.60 | C10: Existing workbook input; source not supplied | E10: 46318 | F10: WACC!D16 | G10: Source required. Document comparable companies, regression source, or a defensible sector estimate.
A11: Pre-tax cost of debt | B11: Model assumption: 11.50% | C11: Existing workbook input; source not supplied | E11: 46318 | F11: WACC!D20 | G11: Source required. If the company has no interest-bearing borrowings, explain why a debt cost remains in the schedule.
A12: Tax rate | B12: Model assumption: 22.50% | C12: Existing workbook forecast assumption | E12: 46318 | F12: WACC!D21; Free Cash Flow!F29:J29 | G12: Validate against applicable tax rules and the company’s effective/marginal tax position.
A13: Forecast assumptions | B13: FY2026–27 to FY2030–31 | C13: Analyst assumptions in workbook; not company guidance | E13: 46318 | F13: Free Cash Flow; Fixed Assets; Net Working Capital | G13: Revenue growth, cost ratios, tax, capex, depreciation and working-capital drivers are assumptions, not sourced forecasts. Explain rationale in the model or README.
A14: Valuation date | B14: 2026-10-23 | C14: Review date used for this workbook update | E14: 46318 | F14: Valuation Summary!B4 | G14: Market price should correspond to this date or the latest available trading date, and should be labelled accordingly.

Sheet Income Statement
B2: Consolidated Statements Of Income - in Millions BDT
C3: 45382 | D3: 45747 | E3: 46112
B4: REVENUE
B5: Total revenue | C5: 14524 | D5: 16309 | E5: 20712
B6: OPERATING EXPENSES
B7: COGS | C7: 6099 | D7: 6598 | E7: 10477
B8: Selling, general and administrative | C8: 2314 | D8: 2667 | E8: 2617
B9: Depreciation & Amortization | C9: 272 | D9: 275 | E9: 262
B10: Preopening expenses | C10: 0 | D10: 0 | E10: 0
B11: Operating Income
B12: OTHER INCOME (EXPENSE) | C12: 40 | D12: 53 | E12: 390
B13: Interest expense | C13: -566 | D13: -94 | E13: -303
B14: Interest income and other, net | C14: 580 | D14: 969 | E14: 296
B15: INCOME BEFORE INCOME TAXES | C15: 5857 | D15: 7572 | E15: 7601
B16: Income Tax Expense (Benefit) | C16: 1250 | D16: 1666 | E16: 1109
B17: Net Income
C18: 4606 | D18: 5906 | E18: 6492
B19: Diluted (shares) | C19: 31.5 | D19: 31.5 | E19: 31.5

Sheet Balance Sheet
B2: Consolidated Balance Sheets - BDT in Millions | C2: 45016 | D2: 45382 | E2: 45747 | F2: 46112
B3: CURRENT ASSETS
B4: Cash and cash equivalents | C4: 2228.81 | D4: 1887.13 | E4: 3092.22 | F4: 1574.94
B5: Other financial assets (current) | C5: 4184.39 | D5: 9018.71 | E5: 5138.33 | F5: 963.9
B6: Accounts Receivable | C6: 1028.62 | D6: 756.71 | E6: 962.31 | F6: 560.37
B7: Inventories | C7: 2528.55 | D7: 3351.47 | E7: 2950.6 | F7: 3531.3
B8: Other current assets | C8: 0 | D8: 0 | E8: 0 | F8: 0
B9: Total current assets | C9: 9977.46 | D9: 15021.38 | E9: 12152.87 | F9: 6636.96
B10: OTHER ASSETS
B11: Property and Equipment, net | C11: 1304.59 | D11: 1414.65 | E11: 1339.74 | F11: 1346.54
B12: Operating lease right-of-use assets | C12: 266.91 | D12: 345.91 | E12: 311.44 | F12: 304.9
B13: Other long-term assets | C13: 94.1 | D13: 94.37 | E13: 96.42 | F13: 93.46
B14: TOTAL ASSETS | C14: 11635.97 | D14: 16906.82 | E14: 13840.39 | F14: 8349.28
B15: CURRENT LIABILITIES
B16: Accounts payable | C16: 7106.38 | D16: 7168.2 | E16: 4897.45 | F16: 4415.03
B17: Accrued salaries and benefits | C17: 25.89 | D17: 21.62 | E17: 48.56 | F17: 91.28
B18: Current tax and other payables | C18: 786.99 | D18: 842.44 | E18: 1099.32 | F18: 736.1
B19: Short-term borrowings | C19: 0 | D19: 450 | E19: 0 | F19: 0
B20: Current portion of long-term debt | C20: 0 | D20: 0 | E20: 0 | F20: 0
B21: Lease liabilities (current) | C21: 57.31 | D21: 38.87 | E21: 58.51 | F21: 59.76
B22: Total current liabilities | C22: 7976.57 | D22: 8521.13 | E22: 6103.84 | F22: 5302.17
B23: OTHER LIABILITIES
B24: Long-term debt, excluding current portion | C24: 0 | D24: 0 | E24: 0 | F24: 0
B25: Long-term operating lease liabilities | C25: 46.4 | D25: 151.87 | E25: 116.31 | F25: 89.49
B26: Other long-term liabilities | C26: 26.68 | D26: 23.74 | E26: 87.58 | F26: 58.9
B27: Total liabilities | C27: 8049.65 | D27: 8696.74 | E27: 6307.73 | F27: 5450.56
B28: EQUITY
B29: Preferred stock | C29: 0 | D29: 0 | E29: 0 | F29: 0
B30: Common Stock (31.5M shares issued and outstanding @10 tk par | C30: 315 | D30: 315 | E30: 315 | F30: 315
B31: Additional paid-in capital (Share premium) | C31: 252 | D31: 252 | E31: 252 | F31: 252
B32: Accumulated other comprehensive loss | C32: 0 | D32: 0 | E32: 0 | F32: 0
B33: Retained earnings | C33: 3019.32 | D33: 7643.07 | E33: 6965.65 | F33: 2331.71
B34: Total stockholders' equity | C34: 3586.32 | D34: 8210.07 | E34: 7532.65 | F34: 2898.71
B35: Noncontrolling interests | C35: 0 | D35: 0 | E35: 0 | F35: 0
B36: Total equity | C36: 3586.32 | D36: 8210.07 | E36: 7532.65 | F36: 2898.71
B37: TOTAL LIABILITIES AND EQUITY | C37: 11635.97 | D37: 16906.81 | E37: 13840.38 | F37: 8349.27

Sheet Cash Flow Statement
B2: Consolidated Statements Of Cash Flows - BDT in Millions
B3: Particulars | C3: 45382 | D3: 45747 | E3: 46112
B4: COllection from customers and others | C4: 14520.19 | D4: 16759.27 | E4: 20216.76
B5: Payment to suppliers and for operating expenses | C5: 7297.44 | D5: 11673.61 | E5: 13400.71
B6: Cash generated from operating activities | C6: =C4-C5 -> 7222.75 | D6: =D4-D5 -> 5085.66 | E6: =E4-E5 -> 6816.05
B7: Interest paid | C7: 148.66 | D7: 76.59 | E7: 0.04
B8: Interest received | C8: 326.83 | D8: 901.07 | E8: 279.88
B9: Income tax paid | C9: 1250.6 | D9: 1303.83 | E9: 1510.32
B10: Net cash from operating activities | C10: =C6-C7-C9+C8 -> 6150.32 | D10: =D6-D7-D9+D8 -> 4606.31 | E10: =E6-E7-E9+E8 -> 5585.57
B11: Cash flows from investing activities
B12: Acquisition of property, plant and equipment | C12: -243.71 | D12: -167.49 | E12: -229.36
B13: Acquisition of intangible assets | C13: 0 | D13: -7.71 | E13: -1.28
B14: Proceeds from disposal of PPE | C14: 4.3 | D14: -1.04 | E14: -0.56
B15: Encashment of/(Investment in) fixed deposits | C15: -4601.09 | D15: 3874.67 | E15: 4326.51
B16: Net cash used in investing activities | C16: =C12+C13+C14+C15 -> -4840.5 | D16: =D12+D13+D14+D15 -> 3698.43 | E16: =E12+E13+E14+E15 -> 4095.31
B17: Cash flows from financing activities | F17: =C10+C16+C21 -> -341.67
B18: Net proceeds from loans and borrowings | C18: 450 | D18: -450 | E18: 0
B19: Dividend paid | C19: -2028.93 | D19: -6583.5 | E19: -11103.7
B20: Payment of lease liability | C20: -72.56 | D20: -66.4 | E20: -94.64
B21: Net cash used in financing activities | C21: =SUM(C18:C20) -> -1651.49 | D21: =SUM(D18:D20) -> -7099.9 | E21: =SUM(E18:E20) -> -11198.34
B22: Net increase in cash and cash equivalents | C22: =C10+C16+C21 -> -341.67 | D22: =D10+D16+D21 -> 1204.84 | E22: =E10+E16+E21 -> -1517.46
B23: Effect of exchange rate fluctuations on cash held | C23: 0 | D23: 0.26 | E23: 0.19
B24: Opening cash and cash equivalents | C24: 2228.81 | D24: 1887.13 | E24: 3092.22
B25: Closing cash and cash equivalents | C25: =C24+C22+C23 -> 1887.14 | D25: =D24+D22+D23 -> 3092.23 | E25: =E24+E22+E23 -> 1574.95
